opensamdpantsplugins/__init__.py
opensamdpantsplugins/jupyter_book/__init__.py
opensamdpantsplugins/jupyter_book/register.py
opensamdpantsplugins-0.1.0.dev0.dist-info/LICENSE
opensamdpantsplugins-0.1.0.dev0.dist-info/WHEEL
opensamdpantsplugins-0.1.0.dev0.dist-info/METADATA
opensamdpantsplugins-0.1.0.dev0.dist-info/RECORD
