Metadata-Version: 2.1
Name: opensamdpantsplugins
Version: 0.1.0.dev0
Summary: Pants plugins created within the OpenSaMD project
Author-email: Simon Biggs <simon.biggs@radiotherapy.ai>
Classifier: License :: OSI Approved :: Apache Software License
Project-URL: Home, https://github.com/OpenSaMD/OpenSaMD
